generallib/__init__.py
generallib/hello.py
busslina_library-0.0.2.dist-info/METADATA
busslina_library-0.0.2.dist-info/WHEEL
busslina_library-0.0.2.dist-info/top_level.txt
busslina_library-0.0.2.dist-info/RECORD
