Metadata-Version: 2.1
Name: busslina-library
Version: 0.0.2
Summary: Busslina Library
Home-page: UNKNOWN
Author: Busslina (Vicente Bincaz)
Author-email: <busslina@gmail.com>
License: UNKNOWN
Keywords: python,general,library
Platform: UNKNOWN
Classifier: Development Status :: 1 - Planning
Classifier: Intended Audience :: Developers
Classifier: Programming Language :: Python :: 3
Classifier: Operating System :: Unix
Classifier: Operating System :: MacOS :: MacOS X
Classifier: Operating System :: Microsoft :: Windows
